pandas_uuid/__init__.py
pandas_uuid/_pyarrow.py
pandas_uuid/py.typed
testing/pandas_uuid/__init__.py
testing/pandas_uuid/_pytest.py
testing/pandas_uuid/py.typed
pandas_uuid-0.1.1.dist-info/METADATA
pandas_uuid-0.1.1.dist-info/WHEEL
pandas_uuid-0.1.1.dist-info/licenses/LICENSE.rst
pandas_uuid-0.1.1.dist-info/RECORD
