Metadata-Version: 2.4
Name: pandas-uuid
Version: 0.1.1
Summary: Pandas ExtensionArray / ExtensionDType for UUIDs.
Project-URL: Source, https://github.com/scverse/pandas-uuid
Project-URL: Documentation, https://icb-pandas-uuid.readthedocs.io/
Author-email: "Philipp A." <flying-sheep@web.de>
License-Expression: MPL-2.0
License-File: LICENSE.rst
Requires-Python: >=3.12
Requires-Dist: numpy
Requires-Dist: pandas
Provides-Extra: pyarrow
Requires-Dist: pyarrow; extra == 'pyarrow'
